{
  "mcpServers": {
    "supabase": {
      "command": "npx",
      "args": ["-y", "@supabase/mcp-server-supabase", "--project-ref", "wtvvuerbhlanswfnuukr"],
      "env": {
        "SUPABASE_ACCESS_TOKEN": "sbp_ae86b33e66a4b719d9ebd71b6bfbdd0e76c16b54"
      }
    },
    "v0": {
      "command": "npx",
      "args": [
        "mcp-remote",
        "https://mcp.v0.dev",
        "--header",
        "Authorization: Bearer v1:rsRwNmKHjd707CVRFSPlBWTI:vcp_46BplNAOKXK9E7dfcnYl5AlJRjo6e9EN9SJByC80hSukWwOpO526CXdq"
      ]
    }
  }
}
